pygwrapper/__init__.py
pygwrapper/animation_convert.py
pygwrapper/physics.py
pygwrapper/win_create.py
pygwrapper-0.0.4.dist-info/LICENSE.txt
pygwrapper-0.0.4.dist-info/METADATA
pygwrapper-0.0.4.dist-info/WHEEL
pygwrapper-0.0.4.dist-info/top_level.txt
pygwrapper-0.0.4.dist-info/RECORD
