Metadata-Version: 2.1
Name: pygwrapper
Version: 0.0.4
Summary: explore endless creativity and development with a combination of pygame and pymunk-based pyhsics 
Home-page: UNKNOWN
Author: SlitherCode
License: UNKNOWN
Platform: UNKNOWN
Classifier: Programming Language :: Python :: 3
Classifier: Operating System :: OS Independent
Requires-Python: >=3.7
Requires-Dist: pygame
Requires-Dist: pymunk
Requires-Dist: pillow
